grabbag
