Metadata-Version: 1.0
Name: grabbag
Version: 0.12.0
Summary: A number of useful utilities that don't seem to exist elsewhere
Home-page: https://github.com/HubSpot/grabbag
Author: prior
Author-email: mprior@hubspot.com
License: LICENSE.txt
Download-URL: https://github.com/HubSpot/grabbag/tarball/v0.12.0
Platform: any
